thelabtyping/__init__.py
thelabtyping/abc.py
thelabtyping/guards.py
thelabtyping/py.typed
thelabtyping/result.py
thelabtyping/api/__init__.py
thelabtyping/api/pagination.py
thelabtyping/api/requests.py
thelabtyping/api/resource.py
thelabtyping/api/responses.py
thelabtyping/api/routing.py
thelabtyping/api/serializers.py
thelabtyping/api/status.py
thelabtyping/api/views.py
thelabtyping/api/openapi/__init__.py
thelabtyping/api/openapi/generator.py
thelabtyping/api/openapi/introspection.py
thelabtyping/api/openapi/models.py
thelabtyping/api/openapi/path_parser.py
thelabtyping/drf/__init__.py
thelabtyping/drf/renderers.py
thelabtyping/tests/__init__.py
thelabtyping/tests/test_abc.py
thelabtyping/tests/test_guards.py
thelabtyping/tests/test_result.py
thelabtyping/tests/api/__init__.py
thelabtyping/tests/api/test_resource.py
thelabtyping/tests/api/test_responses.py
thelabtyping/tests/api/test_routing.py
thelabtyping/tests/api/test_serializers.py
thelabtyping/tests/api/test_status.py
thelabtyping/tests/api/test_views_class_based.py
thelabtyping/tests/api/test_views_functional.py
thelabtyping/tests/api/openapi/__init__.py
thelabtyping/tests/api/openapi/conftest.py
thelabtyping/tests/api/openapi/test_e2e.py
thelabtyping/tests/api/openapi/test_generator.py
thelabtyping/tests/api/openapi/test_introspection.py
thelabtyping/tests/api/openapi/test_models.py
thelabtyping/tests/api/openapi/test_path_parser.py
thelabtyping/tests/drf/__init__.py
thelabtyping/tests/drf/test_renderers.py
thelabtyping/tests/sampleapp/__init__.py
thelabtyping/tests/sampleapp/serializers.py
thelabtyping/tests/sampleapp/urls.py
thelabtyping/tests/sampleapp/views.py
thelabtyping/tests/settings/__init__.py
thelabtyping/tests/settings/sqlite.py
thelabtyping/tests/settings/urls.py
thelab_typing-1.0.1.dist-info/METADATA
thelab_typing-1.0.1.dist-info/WHEEL
thelab_typing-1.0.1.dist-info/licenses/LICENSE
thelab_typing-1.0.1.dist-info/RECORD
