Metadata-Version: 2.4
Name: thelab-typing
Version: 1.0.1
Summary: A collection of utilities related to Python type checking
Project-URL: Homepage, https://gitlab.com/thelabnyc/thelab-typing
Project-URL: Documentation, https://thelabnyc.gitlab.io/thelab-typing
Project-URL: Repository, https://gitlab.com/thelabnyc/thelab-typing
Author-email: thelab <thelabdev@thelab.co>
License: ISC
License-File: LICENSE
Requires-Python: >=3.13
Requires-Dist: pydantic<3.0.0,>=2.12.5
Provides-Extra: django
Requires-Dist: django-stubs-ext>=5.2.8; extra == 'django'
Requires-Dist: django<6.1,>=5.2; extra == 'django'
Provides-Extra: drf
Requires-Dist: django-stubs-ext>=5.2.8; extra == 'drf'
Requires-Dist: djangorestframework>=3.16.1; extra == 'drf'
